concept_formation/__init__.py
concept_formation/cluster.py
concept_formation/cobweb.py
concept_formation/cobweb3.py
concept_formation/continuous_value.py
concept_formation/datasets.py
concept_formation/dummy.py
concept_formation/evaluation.py
concept_formation/preprocessor.py
concept_formation/structure_mapper.py
concept_formation/trestle.py
concept_formation/utils.py
concept_formation/visualize.py
concept_formation/data_files/__init__.py
concept_formation/data_files/congressional_voting.json
concept_formation/data_files/forest_fires.json
concept_formation/data_files/generate_quadruped.py
concept_formation/data_files/human_s_07_success_predictions.csv
concept_formation/data_files/iris.json
concept_formation/data_files/molecule.json
concept_formation/data_files/mushrooms.json
concept_formation/data_files/rb_com_11_continuous.json
concept_formation/data_files/rb_s_07_continuous.json
concept_formation/data_files/rb_s_13_continuous.json
concept_formation/data_files/rb_wb_03_continuous.json
concept_formation/examples/README.rst
concept_formation/examples/__init__.py
concept_formation/examples/acs_simulation.py
concept_formation/examples/cobweb3_cluster_iris.py
concept_formation/examples/cobweb3_cluster_simulated.py
concept_formation/examples/cobweb3_predict_iris.py
concept_formation/examples/cobweb3_regression_example.py
concept_formation/examples/cobweb_cluster_mushroom.py
concept_formation/examples/cobweb_predict_mushroom.py
concept_formation/examples/compare_mse_acc.py
concept_formation/examples/examples_utils.py
concept_formation/examples/li_biswas_experiment.py
concept_formation/examples/regression.py
concept_formation/examples/trestle_cluster_rumbleblocks.py
concept_formation/examples/trestle_cluster_split_search.py
concept_formation/examples/trestle_predict_quadruped.py
concept_formation/examples/trestle_predict_rumbleblocks.py
concept_formation/tests/benchmark_cobweb.py
concept_formation/tests/benchmark_cobweb3.py
concept_formation/tests/test_cobweb.py
concept_formation-0.3.9.dist-info/LICENSE.txt
concept_formation-0.3.9.dist-info/METADATA
concept_formation-0.3.9.dist-info/WHEEL
concept_formation-0.3.9.dist-info/pbr.json
concept_formation-0.3.9.dist-info/top_level.txt
concept_formation-0.3.9.dist-info/RECORD
