Metadata-Version: 2.1
Name: concept-formation
Version: 0.3.9
Summary: A library for doing incremental concept formation using algorithms in the COBWEB family.
Home-page: https://pypi.python.org/pypi/concept_formation
Author: Christopher J. MacLellan, Erik Harpstead
Author-email: maclellan.christopher@gmail.com, whitill29@gmail.com
License: MIT
Project-URL: Documentation, https://concept-formation.readthedocs.io/
Project-URL: Source Code, https://github.com/cmaclell/concept_formation
Keywords: "clustering machine-learning"
Platform: UNKNOWN
Classifier: Development Status :: 4 - Beta
Classifier: Intended Audience :: Science/Research
Classifier: Topic :: Scientific/Engineering :: Artificial Intelligence
Classifier: License :: OSI Approved :: MIT License
Classifier: Programming Language :: Python
Classifier: Programming Language :: Python :: 2
Classifier: Programming Language :: Python :: 2.7
Classifier: Programming Language :: Python :: 3
Classifier: Programming Language :: Python :: 3.7
Classifier: Programming Language :: Python :: Implementation :: PyPy
License-File: LICENSE.txt
Requires-Dist: py-search (>=2.0.0)
Requires-Dist: munkres (>=1.0.12)
